{"offset": 0, "limit": 100, "endOfRecords": true, "results": [{"key": 2480328, "nubKey": 2480328, "nameKey": 8949155, "taxonID": "gbif:2480328", "sourceTaxonKey": 172732971, "kingdom": "Animalia", "phylum": "Chordata", "order": "Charadriiformes", "family": "Charadriidae", "genus": "Pluvialis", "species": "Pluvialis dominica", "kingdomKey": 1, "phylumKey": 44, "classKey": 212, "orderKey": 7192402, "familyKey": 2480210, "genusKey": 2480326, "speciesKey": 2480328, "datasetKey": "d7dddbf4-2cf0-4f39-9b2a-bb099caae36c", "constituentKey": "7ddf754f-d193-4cc9-b351-99906754a03b", "parentKey": 2480326, "parent": "Pluvialis", "basionymKey": 4408585, "basionym": "Charadrius dominicus M\u00fcller, 1776", "scientificName": "Pluvialis dominica (Statius Muller, 1776)", "canonicalName": "Pluvialis dominica", "vernacularName": "American Golden-Plover", "authorship": "(Statius Muller, 1776) ", "nameType": "SCIENTIFIC", "rank": "SPECIES", "origin": "SOURCE", "taxonomicStatus": "ACCEPTED", "nomenclaturalStatus": [], "remarks": "", "publishedIn": "Natursyst. Suppl. p. 116", "numDescendants": 1, "lastCrawled": "2021-11-29T13:11:38.124+00:00", "lastInterpreted": "2021-11-29T12:31:18.519+00:00", "issues": [], "synonym": false, "class": "Aves"}, {"key": 100163928, "nubKey": 2480328, "nameKey": 8949141, "taxonID": "02258", "kingdom": "Animalia", "family": "Pluvialidae", "genus": "Pluvialis", "species": "Pluvialis dominica", "kingdomKey": 128725468, "classKey": 128725469, "familyKey": 128727374, "genusKey": 128727375, "speciesKey": 100163928, "datasetKey": "d7435f14-dfc9-4aaa-bef3-5d1ed22d65bf", "parentKey": 128727375, "parent": "Pluvialis", "scientificName": "Pluvialis dominica", "canonicalName": "Pluvialis dominica", "vernacularName": "American Golden-Plover", "authorship": "", "nameType": "SCIENTIFIC", "rank": "SPECIES", "origin": "SOURCE", "taxonomicStatus": "ACCEPTED", "nomenclaturalStatus": [], "numDescendants": 0, "lastCrawled": "2021-12-01T06:56:44.552+00:00", "lastInterpreted": "2017-04-26T17:15:28.921+00:00", "issues": ["SCIENTIFIC_NAME_ASSEMBLED"], "synonym": false, "class": "Aves"}, {"key": 100206955, "nubKey": 2480328, "nameKey": 8949159, "taxonID": "20732", "order": "Charadriiformes", "family": "Charadriidae", "genus": "Pluvialis", "species": "Pluvialis dominica", "classKey": 100206692, "orderKey": 100206893, "familyKey": 100206929, "genusKey": 100206950, "speciesKey": 100206955, "datasetKey": "79f243f4-9c38-4305-997f-fa8ac3089dba", "parentKey": 100206950, "parent": "Pluvialis", "scientificName": "Pluvialis dominica (Statius M\u00fcller, 1776)", "canonicalName": "Pluvialis dominica", "authorship": "(Statius M\u00fcller, 1776) ", "nameType": "SCIENTIFIC", "rank": "SPECIES", "origin": "SOURCE", "taxonomicStatus": "ACCEPTED", "nomenclaturalStatus": [], "remarks": "parentNameUsage in parentname", "numDescendants": 0, "lastCrawled": "2021-12-01T06:57:03.673+00:00", "lastInterpreted": "2020-04-14T16:56:04.793+00:00", "issues": ["SCIENTIFIC_NAME_ASSEMBLED"], "synonym": false, "class": "Aves"}, {"key": 100481041, "nubKey": 2480328, "nameKey": 8949159, "taxonID": "3942", "kingdom": "Animalia", "phylum": "Chordata", "order": "Charadriiformes", "family": "Charadriidae", "genus": "Pluvialis", "species": "Pluvialis dominica", "kingdomKey": 100382406, "phylumKey": 100478357, "classKey": 100480458, "orderKey": 100480903, "familyKey": 100480999, "genusKey": 100481034, "speciesKey": 100481041, "datasetKey": "39653f3e-8d6b-4a94-a202-859359c164c5", "parentKey": 100481034, "parent": "Pluvialis", "scientificName": "Pluvialis dominica (Statius M\u00fcller, 1776)", "canonicalName": "Pluvialis dominica", "vernacularName": "american golden plover", "authorship": "(Statius M\u00fcller, 1776) ", "nameType": "SCIENTIFIC", "rank": "SPECIES", "origin": "SOURCE", "taxonomicStatus": "ACCEPTED", "nomenclaturalStatus": [], "numDescendants": 0, "references": "http://species.be/en/3942", "lastCrawled": "2021-12-01T07:06:36.177+00:00", "lastInterpreted": "2019-05-24T10:04:56.984+00:00", "issues": ["SCIENTIFIC_NAME_ASSEMBLED"], "synonym": false, "class": "Aves"}, {"key": 101198487, "nubKey": 2480328, "nameKey": 8949159, "taxonID": "100885", "kingdom": "Animalia", "kingdomKey": 135274516, "datasetKey": "1bd42c2b-b58a-4a01-816b-bec8c8977927", "parentKey": 135274516, "parent": "Animalia", "scientificName": "Pluvialis dominica (Statius M\u00fcller, 1776)", "canonicalName": "Pluvialis dominica", "authorship": "(Statius M\u00fcller, 1776) ", "nameType": "SCIENTIFIC", "origin": "SOURCE", "taxonomicStatus": "ACCEPTED", "nomenclaturalStatus": [], "numDescendants": 0, "lastCrawled": "2021-12-01T07:04:28.461+00:00", "lastInterpreted": "2017-10-08T14:28:38.231+00:00", "issues": ["TAXONOMIC_STATUS_INVALID"], "synonym": false}, {"key": 102088374, "nubKey": 2480328, "nameKey": 8949155, "taxonID": "176564", "kingdom": "Animalia", "phylum": "Chordata", "order": "Charadriiformes", "family": "Charadriidae", "genus": "Pluvialis", "species": "Pluvialis dominica", "kingdomKey": 101683523, "phylumKey": 102017110, "classKey": 102085317, "orderKey": 102088140, "familyKey": 102088269, "genusKey": 102088370, "speciesKey": 102088374, "datasetKey": "9ca92552-f23a-41a8-a140-01abaa31c931", "parentKey": 102088370, "parent": "Pluvialis", "scientificName": "Pluvialis dominica (Statius Muller, 1776)", "canonicalName": "Pluvialis dominica", "vernacularName": "American Golden Plover", "authorship": "(Statius Muller, 1776) ", "nameType": "SCIENTIFIC", "rank": "SPECIES", "origin": "SOURCE", "taxonomicStatus": "ACCEPTED", "nomenclaturalStatus": [], "numDescendants": 0, "lastCrawled": "2022-04-23T17:14:47.279+00:00", "lastInterpreted": "2022-04-23T18:04:01.620+00:00", "issues": ["SCIENTIFIC_NAME_ASSEMBLED"], "synonym": false, "class": "Aves"}, {"key": 104107924, "nameKey": 8949141, "taxonID": "240205", "kingdom": "Metazoa", "phylum": "Chordata", "order": "Charadriiformes", "family": "Charadriidae", "genus": "Pluvialis", "species": "Pluvialis dominica", "kingdomKey": 103832354, "phylumKey": 103882489, "classKey": 104106614, "orderKey": 104107620, "familyKey": 104107767, "genusKey": 104107920, "speciesKey": 104107924, "datasetKey": "fab88965-e69d-4491-a04d-e3198b626e52", "parentKey": 104107920, "parent": "Pluvialis", "scientificName": "Pluvialis dominica", "canonicalName": "Pluvialis dominica", "authorship": "", "nameType": "SCIENTIFIC", "rank": "SPECIES", "origin": "SOURCE", "taxonomicStatus": "ACCEPTED", "nomenclaturalStatus": [], "numDescendants": 0, "lastCrawled": "2022-05-10T01:32:18.320+00:00", "lastInterpreted": "2022-05-10T04:20:19.611+00:00", "issues": ["BACKBONE_MATCH_NONE"], "synonym": false, "class": "Aves"}, {"key": 114072249, "nubKey": 2480328, "nameKey": 8949145, "taxonID": "urn:lsid:catalogueoflife.org:taxon:d1d15b37-2dc5-11e0-98c6-2ce70255a436:col20120124", "kingdom": "Animalia", "phylum": "Chordata", "order": "Ciconiiformes", "family": "Charadriidae", "genus": "Pluvialis", "species": "Pluvialis dominica", "kingdomKey": 135219768, "phylumKey": 135219769, "classKey": 135219770, "orderKey": 135219841, "familyKey": 135219856, "genusKey": 135219859, "speciesKey": 114072249, "datasetKey": "87a6a9bf-6188-4742-8049-84bc82a5785e", "parentKey": 135219859, "parent": "Pluvialis", "scientificName": "Pluvialis dominica (M\u00fcller, 1776)", "canonicalName": "Pluvialis dominica", "authorship": "(M\u00fcller, 1776) ", "nameType": "SCIENTIFIC", "rank": "SPECIES", "origin": "SOURCE", "taxonomicStatus": "ACCEPTED", "nomenclaturalStatus": [], "numDescendants": 0, "lastCrawled": "2021-12-01T06:09:53.343+00:00", "lastInterpreted": "2017-10-08T08:19:20.078+00:00", "issues": ["SCIENTIFIC_NAME_ASSEMBLED"], "synonym": false, "class": "Aves"}, {"key": 114099353, "nubKey": 2480328, "nameKey": 8949143, "taxonID": "a88b0102-db2f-407d-9701-bf141187a5cf", "order": "Charadriiformes", "family": "Charadriidae", "genus": "Pluvialis", "species": "Pluvialis dominica", "orderKey": 114099089, "familyKey": 114099117, "genusKey": 114099342, "speciesKey": 114099353, "datasetKey": "3e9a9493-47e4-4dc9-a73a-00c23156b100", "parentKey": 114099342, "parent": "Pluvialis", "scientificName": "Pluvialis dominica (Muller, 1776)", "canonicalName": "Pluvialis dominica", "vernacularName": "American Golden-Plover", "authorship": "(Muller, 1776) ", "nameType": "SCIENTIFIC", "rank": "SPECIES", "origin": "SOURCE", "taxonomicStatus": "ACCEPTED", "nomenclaturalStatus": [], "numDescendants": 2, "lastCrawled": "2022-05-25T08:19:15.390+00:00", "lastInterpreted": "2022-05-25T08:40:19.788+00:00", "issues": [], "synonym": false}, {"key": 114318976, "nubKey": 2480328, "nameKey": 8949153, "taxonID": "urn:lsid:ubio.org:namebank:3851166", "kingdom": "Animalia", "phylum": "Chordata", "order": "Charadriiformes", "family": "Charadriidae", "genus": "Pluvialis", "kingdomKey": 135215737, "phylumKey": 135215738, "classKey": 135215739, "orderKey": 135215877, "familyKey": 135215878, "genusKey": 135215880, "datasetKey": "1079ebef-9efc-448f-a2fe-56c6d72847c4", "parentKey": 135215880, "parent": "Pluvialis", "scientificName": "Pluvialis dominica (Statius Muller) 1776", "canonicalName": "Pluvialis dominica", "authorship": "(Statius Muller, 1776) ", "nameType": "SCIENTIFIC", "origin": "SOURCE", "taxonomicStatus": "ACCEPTED", "nomenclaturalStatus": [], "accordingTo": "Taxonom\u00eda y estado taxon\u00f3mico tomado de: Species 2000 & ITIS Catalogue of Life: 2041", "numDescendants": 0, "lastCrawled": "2021-12-01T06:09:16.216+00:00", "lastInterpreted": "2017-10-08T08:17:53.489+00:00", "issues": ["SCIENTIFIC_NAME_ASSEMBLED"], "synonym": false, "class": "Aves"}, {"key": 114887128, "nubKey": 2480328, "nameKey": 8949145, "taxonID": "6604-sp184", "kingdom": "Animalia", "phylum": "Chordata", "genus": "Pluvialis", "kingdomKey": 135079013, "phylumKey": 135079014, "classKey": 135079015, "genusKey": 135079183, "datasetKey": "0b12b11d-87ba-4246-a21d-e081302c1df9", "parentKey": 135079183, "parent": "Pluvialis", "scientificName": "Pluvialis dominica (M\u00fcller, 1776)", "canonicalName": "Pluvialis dominica", "authorship": "(M\u00fcller, 1776) ", "nameType": "SCIENTIFIC", "origin": "SOURCE", "taxonomicStatus": "ACCEPTED", "nomenclaturalStatus": [], "numDescendants": 0, "references": "http://dx.doi.org/10.3897/BDJ.3.e6604", "lastCrawled": "2021-12-01T06:08:57.223+00:00", "lastInterpreted": "2017-09-30T16:34:43.365+00:00", "issues": [], "synonym": false, "class": "Aves"}, {"key": 114904968, "nubKey": 2480328, "nameKey": 8949141, "taxonID": "http://eol.org/pages/1049365", "kingdom": "Animalia", "phylum": "Chordata", "order": "Charadriiformes", "family": "Charadriidae", "genus": "Pluvialis", "species": "Pluvialis dominica", "kingdomKey": 144235952, "phylumKey": 144237109, "classKey": 144237303, "orderKey": 144237416, "familyKey": 144237431, "genusKey": 144237433, "speciesKey": 114904968, "datasetKey": "ee2aac07-de9a-47a2-b828-37430d537633", "parentKey": 144237433, "parent": "Pluvialis", "scientificName": "Pluvialis dominica", "canonicalName": "Pluvialis dominica", "authorship": "", "nameType": "SCIENTIFIC", "rank": "SPECIES", "origin": "SOURCE", "taxonomicStatus": "ACCEPTED", "nomenclaturalStatus": [], "remarks": "Registros en el SIRAP-EC: 1", "numDescendants": 0, "lastCrawled": "2021-12-01T06:09:06.217+00:00", "lastInterpreted": "2018-06-04T23:29:45.522+00:00", "issues": ["TAXONOMIC_STATUS_INVALID"], "synonym": false, "class": "Aves"}, {"key": 116806264, "nubKey": 2480328, "nameKey": 8949159, "taxonID": "http://services.snsb.info/DTNtaxonlists/rest/v0.1/names/DiversityTaxonNames_TaxaVaria/10187/", "kingdom": "Animalia", "phylum": "Chordata", "order": "Charadriiformes", "family": "Charadriidae", "genus": "Pluvialis", "species": "Pluvialis dominica", "kingdomKey": 132774790, "phylumKey": 116785007, "classKey": 116785780, "orderKey": 116805926, "familyKey": 116806236, "genusKey": 116806262, "speciesKey": 116806264, "datasetKey": "88f4e35a-bdf8-4aa2-9a1b-56401d4eed15", "parentKey": 116806262, "parent": "Pluvialis", "scientificName": "Pluvialis dominica (Statius M\u00fcller, 1776)", "canonicalName": "Pluvialis dominica", "authorship": "(Statius M\u00fcller, 1776) ", "nameType": "SCIENTIFIC", "rank": "SPECIES", "origin": "SOURCE", "taxonomicStatus": "ACCEPTED", "nomenclaturalStatus": [], "numDescendants": 0, "references": "http://services.snsb.info/DTNtaxonlists/rest/v0.1/names/DiversityTaxonNames_TaxaVaria/10187/", "lastCrawled": "2022-05-25T07:43:11.174+00:00", "lastInterpreted": "2022-05-25T07:45:03.591+00:00", "issues": [], "synonym": false, "class": "Aves"}, {"key": 116901748, "nubKey": 2480328, "nameKey": 8949141, "taxonID": "94da04c8-9e26-4ef6-ab72-f82a4efd01fe", "order": "Charadriiformes", "family": "Charadriidae", "genus": "Pluvialis", "species": "Pluvialis dominica", "classKey": 116891945, "orderKey": 116900787, "familyKey": 116901726, "genusKey": 116901738, "speciesKey": 116901748, "datasetKey": "71667154-257d-4d8e-a2a5-711aaf9b2d74", "parentKey": 116901738, "parent": "Pluvialis", "scientificName": "Pluvialis dominica", "canonicalName": "Pluvialis dominica", "vernacularName": "American golden plover", "authorship": "", "nameType": "SCIENTIFIC", "rank": "SPECIES", "origin": "SOURCE", "taxonomicStatus": "ACCEPTED", "nomenclaturalStatus": [], "numDescendants": 0, "lastCrawled": "2022-05-25T08:19:13.097+00:00", "lastInterpreted": "2022-05-25T08:21:56.482+00:00", "issues": [], "synonym": false, "class": "Aves"}, {"key": 119562465, "nubKey": 2480328, "nameKey": 8949141, "taxonID": "urn:lsid:catalogueoflife.org:taxon:d1d15b37-2dc5-11e0-98c6-2ce70255a436:col20110201", "kingdom": "Animalia", "phylum": "Chordata", "order": "Charadriiformes", "family": "Charadriidae", "genus": "Pluvialis", "species": "Pluvialis dominica", "kingdomKey": 135272759, "phylumKey": 135272760, "classKey": 135272839, "orderKey": 135273088, "familyKey": 135273099, "genusKey": 135273102, "speciesKey": 119562465, "datasetKey": "d922f0cd-fae6-4600-8daa-2b41bb4f76ad", "parentKey": 135273102, "parent": "Pluvialis", "scientificName": "Pluvialis dominica", "canonicalName": "Pluvialis dominica", "authorship": "", "nameType": "SCIENTIFIC", "rank": "SPECIES", "origin": "SOURCE", "taxonomicStatus": "ACCEPTED", "nomenclaturalStatus": [], "numDescendants": 0, "lastCrawled": "2021-12-01T06:56:36.291+00:00", "lastInterpreted": "2017-10-08T13:04:43.753+00:00", "issues": [], "synonym": false, "class": "Aves"}, {"key": 119650626, "nubKey": 2480328, "nameKey": 8949145, "taxonID": "urn:lsid:catalogueoflife.org:taxon:d1d15b37-2dc5-11e0-98c6-2ce70255a436:col20120124", "kingdom": "Animalia", "phylum": "Chordata", "order": "Charadriiformes", "family": "Charadriidae", "genus": "Pluvialis", "kingdomKey": 144209400, "phylumKey": 144209403, "classKey": 144209405, "orderKey": 144209479, "familyKey": 144209489, "genusKey": 144209491, "datasetKey": "47083374-d545-4f4e-8f4f-1fd881d13fbd", "parentKey": 144209491, "parent": "Pluvialis", "scientificName": "Pluvialis dominica (M\u00fcller, 1776)", "canonicalName": "Pluvialis dominica", "authorship": "(M\u00fcller, 1776) ", "nameType": "SCIENTIFIC", "origin": "SOURCE", "taxonomicStatus": "ACCEPTED", "nomenclaturalStatus": [], "remarks": "ID del tax\u00f3n tomado de CoL", "numDescendants": 0, "lastCrawled": "2021-12-01T06:56:04.917+00:00", "lastInterpreted": "2018-06-01T15:10:33.236+00:00", "issues": ["SCIENTIFIC_NAME_ASSEMBLED"], "synonym": false, "class": "Aves"}, {"key": 120732024, "nubKey": 2480328, "nameKey": 8949141, "taxonID": "urn:lsid:catalogueoflife.org:taxon:866eb53c-9c14-11e4-8753-020044200006:col20150212", "kingdom": "Animalia", "phylum": "Chordata", "order": "Charadriiformes", "family": "Charadriidae", "genus": "Pluvialis", "species": "Pluvialis dominica", "kingdomKey": 134996071, "phylumKey": 134996072, "classKey": 134996073, "orderKey": 134996169, "familyKey": 134996170, "genusKey": 134996172, "speciesKey": 120732024, "datasetKey": "dd6c4260-c134-4548-af43-dbd00fb24b1f", "parentKey": 134996172, "parent": "Pluvialis", "scientificName": "Pluvialis dominica", "canonicalName": "Pluvialis dominica", "authorship": "", "nameType": "SCIENTIFIC", "rank": "SPECIES", "origin": "SOURCE", "taxonomicStatus": "ACCEPTED", "nomenclaturalStatus": [], "numDescendants": 0, "lastCrawled": "2021-12-01T04:06:03.515+00:00", "lastInterpreted": "2017-09-30T03:25:01.415+00:00", "issues": [], "synonym": false, "class": "Aves"}, {"key": 123211204, "nubKey": 2480328, "nameKey": 8949141, "taxonID": "Pluvialis dominica", "kingdom": "Animalia", "order": "Charadriiformes", "family": "Charadriidae", "species": "Pluvialis dominica", "kingdomKey": 167183684, "orderKey": 167183785, "familyKey": 167183801, "speciesKey": 123211204, "datasetKey": "a5dd063e-f45b-4a54-8b94-8fa3adf7f1e1", "parentKey": 167183801, "parent": "Charadriidae", "scientificName": "Pluvialis dominica", "canonicalName": "Pluvialis dominica", "vernacularName": "American Golden Plover", "authorship": "", "nameType": "SCIENTIFIC", "rank": "SPECIES", "origin": "SOURCE", "taxonomicStatus": "ACCEPTED", "nomenclaturalStatus": [], "numDescendants": 0, "lastCrawled": "2021-12-01T04:00:25.093+00:00", "lastInterpreted": "2020-08-19T04:34:12.373+00:00", "issues": [], "synonym": false}, {"key": 123258094, "nubKey": 2480328, "nameKey": 8949159, "taxonID": "96882", "kingdom": "Animalia", "phylum": "Chordata", "order": "Charadriiformes", "family": "Charadriidae", "genus": "Pluvialis", "species": "Pluvialis dominica", "kingdomKey": 123221224, "phylumKey": 123221506, "classKey": 123246841, "orderKey": 123256752, "familyKey": 123258043, "genusKey": 123258076, "speciesKey": 123258094, "datasetKey": "90d9e8a6-0ce1-472d-b682-3451095dbc5a", "parentKey": 123258076, "parent": "Pluvialis", "basionymKey": 123258097, "basionym": "Charadrius dominica Statius M\u00fcller, 1776", "scientificName": "Pluvialis dominica (Statius M\u00fcller, 1776)", "canonicalName": "Pluvialis dominica", "authorship": "(Statius M\u00fcller, 1776) ", "nameType": "SCIENTIFIC", "rank": "SPECIES", "origin": "SOURCE", "taxonomicStatus": "ACCEPTED", "nomenclaturalStatus": [], "numDescendants": 0, "references": "http://www.faunaeur.org/full_results.php?id=96882", "lastCrawled": "2021-12-01T07:25:32.107+00:00", "lastInterpreted": "2021-02-02T15:51:53.647+00:00", "issues": [], "synonym": false, "class": "Aves"}, {"key": 128534346, "nubKey": 2480328, "nameKey": 8949155, "taxonID": "urn:lsid:catalogueoflife.org:taxon:64381838-e478-11e5-86e7-bc764e092680:col20150315", "kingdom": "Animalia", "phylum": "Chordata", "order": "Charadriiformes", "family": "Charadriidae", "genus": "Pluvialis", "species": "Pluvialis dominica", "kingdomKey": 144239699, "phylumKey": 144239790, "classKey": 144240088, "orderKey": 144240435, "familyKey": 144240438, "genusKey": 144240443, "speciesKey": 128534346, "datasetKey": "1a15d46d-db0b-48bf-8e49-6ef1cfd08128", "parentKey": 144240443, "parent": "Pluvialis", "scientificName": "Pluvialis dominica (Statius Muller, 1776)", "canonicalName": "Pluvialis dominica", "authorship": "(Statius Muller, 1776) ", "nameType": "SCIENTIFIC", "rank": "SPECIES", "origin": "SOURCE", "taxonomicStatus": "ACCEPTED", "nomenclaturalStatus": [], "numDescendants": 0, "lastCrawled": "2021-12-01T03:08:53.132+00:00", "lastInterpreted": "2018-06-05T03:07:38.631+00:00", "issues": ["TAXONOMIC_STATUS_INVALID", "SCIENTIFIC_NAME_ASSEMBLED"], "synonym": false, "class": "Aves"}, {"key": 133140777, "nubKey": 2480328, "nameKey": 8949141, "taxonID": "3926", "kingdom": "Animalia", "order": "Charadriiformes", "family": "Charadriidae", "species": "Pluvialis dominica", "kingdomKey": 135274602, "classKey": 135274603, "orderKey": 135274646, "familyKey": 135274667, "speciesKey": 133140777, "datasetKey": "47f16512-bf31-410f-b272-d151c996b2f6", "parentKey": 135274667, "parent": "Charadriidae", "scientificName": "Pluvialis dominica", "canonicalName": "Pluvialis dominica", "vernacularName": "American Golden-Plover", "authorship": "", "nameType": "SCIENTIFIC", "rank": "SPECIES", "origin": "SOURCE", "taxonomicStatus": "ACCEPTED", "nomenclaturalStatus": [], "numDescendants": 0, "lastCrawled": "2021-12-01T06:58:22.997+00:00", "lastInterpreted": "2017-10-08T14:56:51.499+00:00", "issues": [], "synonym": false, "class": "Aves"}, {"key": 143553692, "nubKey": 2480328, "nameKey": 18211959, "taxonID": "368020", "phylum": "Chordata", "order": "Charadriiformes", "family": "Charadriidae", "genus": "Pluvialis", "species": "Charadrius dominicus", "phylumKey": 121445866, "classKey": 121497163, "orderKey": 121512789, "familyKey": 121513275, "genusKey": 121513284, "speciesKey": 121513293, "datasetKey": "c33ce2f2-c3cc-43a5-a380-fe4526d63650", "parentKey": 121513284, "parent": "Pluvialis", "acceptedKey": 121513293, "accepted": "Charadrius dominicus (Mueller, 1776)", "basionymKey": 121513293, "basionym": "Charadrius dominicus (Mueller, 1776)", "scientificName": "Pluvialis dominica (Mueller, 1776)", "canonicalName": "Pluvialis dominica", "vernacularName": "American golden plover", "authorship": "(Mueller, 1776) ", "nameType": "SCIENTIFIC", "rank": "SPECIES", "origin": "SOURCE", "taxonomicStatus": "SYNONYM", "nomenclaturalStatus": [], "accordingTo": "accretion,modification of parts", "numDescendants": 0, "lastCrawled": "2022-05-25T22:49:57.862+00:00", "lastInterpreted": "2022-05-25T23:22:19.436+00:00", "issues": ["SCIENTIFIC_NAME_ASSEMBLED"], "synonym": true, "class": "Aves"}, {"key": 144105747, "nameKey": 8949155, "taxonID": "300115", "genus": "Pluvialis", "species": "Pluvialis dominica", "genusKey": 144105746, "speciesKey": 144105747, "datasetKey": "cbb6498e-8927-405a-916b-576d00a6289b", "parentKey": 144105746, "parent": "Pluvialis", "scientificName": "Pluvialis dominica (Statius Muller, 1776)", "canonicalName": "Pluvialis dominica", "vernacularName": "American golden plover", "authorship": "(Statius Muller, 1776) ", "nameType": "SCIENTIFIC", "rank": "SPECIES", "origin": "SOURCE", "taxonomicStatus": "ACCEPTED", "nomenclaturalStatus": [], "remarks": "Failed to retrieve taxonomy from {}", "numDescendants": 0, "references": "http://en.wikipedia.org/wiki/American_golden_plover", "lastCrawled": "2022-05-18T20:08:56.617+00:00", "lastInterpreted": "2022-05-18T20:54:33.414+00:00", "issues": ["SCIENTIFIC_NAME_ASSEMBLED", "BACKBONE_MATCH_NONE"], "synonym": false}, {"key": 146055806, "nubKey": 2480328, "nameKey": 8949155, "taxonID": "gbif.org/species/2480328", "kingdom": "Animalia", "phylum": "Chordata", "order": "Charadriiformes", "family": "Charadriidae", "genus": "Pluvialis", "species": "Pluvialis dominica", "kingdomKey": 162057911, "phylumKey": 162057912, "classKey": 162057913, "orderKey": 162058560, "familyKey": 162058609, "genusKey": 162058612, "speciesKey": 146055806, "datasetKey": "6c9c4b08-4cec-4160-a708-7f16060d7db0", "parentKey": 162058612, "parent": "Pluvialis", "scientificName": "Pluvialis dominica (Statius Muller, 1776)", "canonicalName": "Pluvialis dominica", "authorship": "(Statius Muller, 1776) ", "nameType": "SCIENTIFIC", "rank": "SPECIES", "origin": "SOURCE", "taxonomicStatus": "ACCEPTED", "nomenclaturalStatus": [], "numDescendants": 0, "lastCrawled": "2021-12-01T02:37:28.511+00:00", "lastInterpreted": "2020-02-07T20:35:08.067+00:00", "issues": ["SCIENTIFIC_NAME_ASSEMBLED", "DESCRIPTION_INVALID", "DISTRIBUTION_INVALID"], "synonym": false, "class": "Aves"}, {"key": 146766396, "nubKey": 2480328, "nameKey": 8949141, "taxonID": "635", "species": "Pluvialis dominica", "speciesKey": 146766396, "datasetKey": "0776184c-45ea-49c4-a4f0-3b812a20aba9", "scientificName": "Pluvialis dominica", "canonicalName": "Pluvialis dominica", "authorship": "", "nameType": "SCIENTIFIC", "rank": "SPECIES", "origin": "SOURCE", "taxonomicStatus": "ACCEPTED", "nomenclaturalStatus": [], "numDescendants": 0, "lastCrawled": "2021-12-01T03:51:08.571+00:00", "lastInterpreted": "2018-08-01T15:02:27.998+00:00", "issues": [], "synonym": false}, {"key": 152356452, "nubKey": 2480328, "nameKey": 8949155, "taxonID": "gbif.org:species:9757314", "kingdom": "Animalia", "phylum": "Chordata", "order": "Charadriiformes", "family": "Charadriidae", "genus": "Pluvialis", "species": "Pluvialis dominica", "kingdomKey": 157159994, "phylumKey": 157161584, "classKey": 157161586, "orderKey": 157162444, "familyKey": 157162467, "genusKey": 157162468, "speciesKey": 152356452, "datasetKey": "8b4ecd20-850f-473e-af8c-dbf5d1e76932", "parentKey": 157162468, "parent": "Pluvialis", "scientificName": "Pluvialis dominica (Statius Muller, 1776)", "canonicalName": "Pluvialis dominica", "authorship": "(Statius Muller, 1776) ", "nameType": "SCIENTIFIC", "rank": "SPECIES", "origin": "SOURCE", "taxonomicStatus": "ACCEPTED", "nomenclaturalStatus": [], "remarks": "Aves", "numDescendants": 0, "lastCrawled": "2021-12-01T02:25:34.105+00:00", "lastInterpreted": "2019-05-16T08:19:50.474+00:00", "issues": ["SCIENTIFIC_NAME_ASSEMBLED"], "synonym": false, "class": "Aves"}, {"key": 152437862, "nubKey": 2480328, "nameKey": 8949159, "taxonID": "464943050", "kingdom": "Animalia", "phylum": "Chordata", "order": "Charadriiformes", "family": "Charadriidae", "genus": "Pluvialis", "species": "Pluvialis dominica", "kingdomKey": 195556280, "phylumKey": 195557217, "classKey": 195557526, "orderKey": 195558501, "familyKey": 195558527, "genusKey": 195558540, "speciesKey": 152437862, "datasetKey": "4dd32523-a3a3-43b7-84df-4cda02f15cf7", "parentKey": 195558540, "parent": "Pluvialis", "scientificName": "Pluvialis dominica (Statius M\u00fcller, 1776)", "canonicalName": "Pluvialis dominica", "authorship": "(Statius M\u00fcller, 1776) ", "nameType": "SCIENTIFIC", "rank": "SPECIES", "origin": "SOURCE", "taxonomicStatus": "ACCEPTED", "nomenclaturalStatus": [], "numDescendants": 0, "references": "https://nederlandsesoorten.nl/nsr/concept/000464943050", "lastCrawled": "2022-05-22T10:22:34.463+00:00", "lastInterpreted": "2022-05-22T10:26:32.240+00:00", "issues": [], "synonym": false, "class": "Aves"}, {"key": 155306006, "nubKey": 2480328, "nameKey": 8949145, "taxonID": "urn:lsid:marinespecies.org:taxname:159136", "kingdom": "Animalia", "phylum": "Chordata", "order": "Charadriiformes", "family": "Charadriidae", "genus": "Pluvialis", "species": "Pluvialis dominica", "kingdomKey": 154946057, "phylumKey": 155295572, "classKey": 155304455, "orderKey": 155305509, "familyKey": 155305918, "genusKey": 155305993, "speciesKey": 155306006, "datasetKey": "2d59e5db-57ad-41ff-97d6-11f5fb264527", "parentKey": 155305993, "parent": "Pluvialis", "scientificName": "Pluvialis dominica (M\u00fcller, 1776)", "canonicalName": "Pluvialis dominica", "vernacularName": "American golden plover", "authorship": "(M\u00fcller, 1776) ", "nameType": "SCIENTIFIC", "rank": "SPECIES", "origin": "SOURCE", "taxonomicStatus": "ACCEPTED", "nomenclaturalStatus": [], "numDescendants": 0, "references": "https://www.marinespecies.org/aphia.php?p=taxdetails&id=159136", "lastCrawled": "2022-05-02T22:31:12.330+00:00", "lastInterpreted": "2022-05-03T00:35:22.667+00:00", "issues": ["SCIENTIFIC_NAME_ASSEMBLED", "CLASSIFICATION_NOT_APPLIED"], "synonym": false, "class": "Aves"}, {"key": 156109290, "nubKey": 2480328, "nameKey": 8949141, "taxonID": "Oiseaux_SN_511", "kingdom": "Animalia", "genus": "Pluvialis", "species": "Pluvialis dominica", "kingdomKey": 156108990, "genusKey": 156109289, "speciesKey": 156109290, "datasetKey": "c0d879f3-66e0-4bf0-8288-107d74cbfca2", "parentKey": 156109289, "parent": "Pluvialis", "scientificName": "Pluvialis dominica", "canonicalName": "Pluvialis dominica", "authorship": "", "nameType": "SCIENTIFIC", "rank": "SPECIES", "origin": "SOURCE", "taxonomicStatus": "ACCEPTED", "nomenclaturalStatus": [], "numDescendants": 0, "lastCrawled": "2021-12-01T02:13:15.412+00:00", "lastInterpreted": "2019-04-06T17:54:41.499+00:00", "issues": [], "synonym": false}, {"key": 158203767, "nubKey": 2480328, "nameKey": 24683033, "taxonID": "http://bins.boldsystems.org/index.php/Taxbrowser_Taxonpage?taxid=10129", "kingdom": "Animalia", "phylum": "Chordata", "order": "Charadriiformes", "family": "Charadriidae", "genus": "Pluvialis", "species": "Pluvialis dominica", "kingdomKey": 157533281, "phylumKey": 158135805, "classKey": 158183130, "orderKey": 158203336, "familyKey": 158203696, "genusKey": 158203760, "speciesKey": 158203767, "datasetKey": "4cec8fef-f129-4966-89b7-4f8439aba058", "parentKey": 158203760, "parent": "Pluvialis", "scientificName": "Pluvialis dominica Statius Muller, 1776", "canonicalName": "Pluvialis dominica", "authorship": "Statius Muller, 1776", "nameType": "SCIENTIFIC", "rank": "SPECIES", "origin": "SOURCE", "taxonomicStatus": "ACCEPTED", "nomenclaturalStatus": [], "numDescendants": 1, "references": "http://bins.boldsystems.org/index.php/Taxbrowser_Taxonpage?taxid=10129", "lastCrawled": "2022-02-22T13:38:13.223+00:00", "lastInterpreted": "2022-02-22T14:56:38.585+00:00", "issues": ["SCIENTIFIC_NAME_ASSEMBLED"], "synonym": false, "class": "Aves"}, {"key": 159148256, "nubKey": 2480328, "nameKey": 8949145, "taxonID": "13390AVES", "kingdom": "Animalia", "phylum": "Chordata", "order": "Charadriiformes", "family": "Charadriidae", "genus": "Pluvialis", "species": "Pluvialis dominica", "kingdomKey": 183550945, "phylumKey": 183550946, "classKey": 159146404, "orderKey": 159148064, "familyKey": 159148249, "genusKey": 159148254, "speciesKey": 159148256, "datasetKey": "c6846748-a99f-4de3-bec5-51cff7272f3b", "parentKey": 159148254, "parent": "Pluvialis", "scientificName": "Pluvialis dominica (M\u00fcller, 1776)", "canonicalName": "Pluvialis dominica", "authorship": "(M\u00fcller, 1776) ", "nameType": "SCIENTIFIC", "rank": "SPECIES", "origin": "SOURCE", "taxonomicStatus": "ACCEPTED", "nomenclaturalStatus": [], "publishedIn": "Natursyst., Suppl.: 116. 1776", "accordingTo": "American Ornithological Society, 2018", "numDescendants": 1, "lastCrawled": "2021-12-01T02:02:08.287+00:00", "lastInterpreted": "2021-07-16T22:00:55.766+00:00", "issues": ["SCIENTIFIC_NAME_ASSEMBLED", "DISTRIBUTION_INVALID"], "synonym": false, "class": "Aves"}, {"key": 159938355, "nubKey": 2480328, "nameKey": 19124980, "taxonID": "urn:lsid:dyntaxa.se:Taxon:205599", "kingdom": "Animalia", "order": "Charadriiformes", "family": "Charadriidae", "genus": "Pluvialis", "species": "Pluvialis dominica", "kingdomKey": 159935719, "classKey": 159935840, "orderKey": 159937662, "familyKey": 159938330, "genusKey": 159938350, "speciesKey": 159938355, "datasetKey": "de8934f4-a136-481c-a87a-b0b202b80a31", "parentKey": 159938350, "parent": "Pluvialis", "scientificName": "Pluvialis dominica (P.L.S.M\u00fcller, 1776)", "canonicalName": "Pluvialis dominica", "vernacularName": "American Golden Plover", "authorship": "(P.L.S.M\u00fcller, 1776) ", "nameType": "SCIENTIFIC", "rank": "SPECIES", "origin": "SOURCE", "taxonomicStatus": "ACCEPTED", "nomenclaturalStatus": ["VALIDLY_PUBLISHED"], "remarks": "\"Monotypisk. \"", "numDescendants": 0, "lastCrawled": "2022-05-25T19:32:27.587+00:00", "lastInterpreted": "2022-05-25T19:41:58.262+00:00", "issues": ["SCIENTIFIC_NAME_ASSEMBLED"], "synonym": false, "class": "Aves"}, {"key": 160796227, "nubKey": 2480328, "nameKey": 8949155, "taxonID": "2480328", "kingdom": "Animalia", "phylum": "Chordata", "order": "Charadriiformes", "family": "Charadriidae", "genus": "Pluvialis", "species": "Pluvialis dominica", "kingdomKey": 160779655, "phylumKey": 160795250, "classKey": 160795592, "orderKey": 160796108, "familyKey": 160796224, "genusKey": 160796225, "speciesKey": 160796227, "datasetKey": "0b1735ff-6a66-454b-8686-cae1cbc732a2", "parentKey": 160796225, "parent": "Pluvialis", "scientificName": "Pluvialis dominica (Statius Muller, 1776)", "canonicalName": "Pluvialis dominica", "authorship": "(Statius Muller, 1776) ", "nameType": "SCIENTIFIC", "rank": "SPECIES", "origin": "SOURCE", "taxonomicStatus": "ACCEPTED", "nomenclaturalStatus": [], "numDescendants": 0, "lastCrawled": "2021-12-22T14:31:37.358+00:00", "lastInterpreted": "2021-12-22T14:33:13.659+00:00", "issues": ["SCIENTIFIC_NAME_ASSEMBLED"], "synonym": false, "class": "Aves"}, {"key": 161394882, "nubKey": 2480328, "nameKey": 8949159, "taxonID": "3158", "kingdom": "Animalia", "phylum": "Chordata", "order": "Charadriiformes", "family": "Charadriidae", "genus": "Pluvialis", "species": "Pluvialis dominica", "kingdomKey": 134521164, "phylumKey": 161376443, "classKey": 161391677, "orderKey": 161393584, "familyKey": 161394804, "genusKey": 161394867, "speciesKey": 161394882, "datasetKey": "0e61f8fe-7d25-4f81-ada7-d970bbb2c6d6", "parentKey": 161394867, "parent": "Pluvialis", "scientificName": "Pluvialis dominica (Statius M\u00fcller, 1776)", "canonicalName": "Pluvialis dominica", "authorship": "(Statius M\u00fcller, 1776) ", "nameType": "SCIENTIFIC", "rank": "SPECIES", "origin": "SOURCE", "taxonomicStatus": "ACCEPTED", "nomenclaturalStatus": [], "accordingTo": "TAXREF", "numDescendants": 0, "references": "https://inpn.mnhn.fr/espece/cd_nom/3158", "lastCrawled": "2022-03-14T16:21:20.448+00:00", "lastInterpreted": "2022-03-14T17:12:18.639+00:00", "issues": ["SCIENTIFIC_NAME_ASSEMBLED"], "synonym": false, "class": "Aves"}, {"key": 162075170, "nubKey": 2480328, "nameKey": 8949155, "taxonID": "gbif.org/species/2480328", "kingdom": "Animalia", "phylum": "Chordata", "order": "Charadriiformes", "family": "Charadriidae", "genus": "Pluvialis", "species": "Pluvialis dominica", "kingdomKey": 162076428, "phylumKey": 162076429, "classKey": 162076430, "orderKey": 162076558, "familyKey": 162076597, "genusKey": 162076599, "speciesKey": 162075170, "datasetKey": "17640146-2643-4f00-9e5d-52b5302c238c", "parentKey": 162076599, "parent": "Pluvialis", "scientificName": "Pluvialis dominica (Statius Muller, 1776)", "canonicalName": "Pluvialis dominica", "authorship": "(Statius Muller, 1776) ", "nameType": "SCIENTIFIC", "rank": "SPECIES", "origin": "SOURCE", "taxonomicStatus": "ACCEPTED", "nomenclaturalStatus": [], "numDescendants": 0, "lastCrawled": "2021-12-01T01:42:16.200+00:00", "lastInterpreted": "2020-02-12T01:51:16.064+00:00", "issues": ["SCIENTIFIC_NAME_ASSEMBLED", "DESCRIPTION_INVALID"], "synonym": false, "class": "Aves"}, {"key": 163284880, "nubKey": 2480328, "nameKey": 8949155, "taxonID": "https://www.gbif.org/species/2480328", "kingdom": "Animalia", "phylum": "Chordata", "order": "Charadriiformes", "family": "Charadriidae", "genus": "Pluvialis", "species": "Pluvialis dominica", "kingdomKey": 182244810, "phylumKey": 182244818, "classKey": 182245458, "orderKey": 182245534, "familyKey": 182245536, "genusKey": 182245537, "speciesKey": 163284880, "datasetKey": "384120be-ef7c-4787-9ff0-cb1b3f588b26", "parentKey": 182245537, "parent": "Pluvialis", "scientificName": "Pluvialis dominica (Statius Muller, 1776)", "canonicalName": "Pluvialis dominica", "authorship": "(Statius Muller, 1776) ", "nameType": "SCIENTIFIC", "rank": "SPECIES", "origin": "SOURCE", "taxonomicStatus": "ACCEPTED", "nomenclaturalStatus": [], "numDescendants": 0, "lastCrawled": "2021-12-01T01:44:25.306+00:00", "lastInterpreted": "2021-05-20T14:32:18.832+00:00", "issues": ["SCIENTIFIC_NAME_ASSEMBLED", "DISTRIBUTION_INVALID"], "synonym": false, "class": "Aves"}, {"key": 164480264, "nubKey": 2480328, "nameKey": 32827190, "taxonID": "urn:lsid:ubio.org:namebank:3851166", "kingdom": "Animalia", "phylum": "Chordata", "order": "Charadriiformes", "family": "Charadriidae", "genus": "Pluvialis", "species": "Pluvialis dominica", "kingdomKey": 164485877, "phylumKey": 164485878, "classKey": 164485879, "orderKey": 164486034, "familyKey": 164486048, "genusKey": 164486052, "speciesKey": 164480264, "datasetKey": "701da598-f9f0-4fc5-876a-5a23da88a131", "parentKey": 164486052, "parent": "Pluvialis", "scientificName": "Pluvialis dominica (Statius Muller), 1776", "canonicalName": "Pluvialis dominica", "authorship": "(Statius Muller) , 1776", "nameType": "SCIENTIFIC", "rank": "SPECIES", "origin": "SOURCE", "taxonomicStatus": "ACCEPTED", "nomenclaturalStatus": [], "accordingTo": "Remsen, J. V., Jr., C. D. Cadena, A. Jaramillo, M. Nores, J. F. Pacheco, J. P\u00e9rez-Em\u00e1n, M. B. Robbins, F. G. Stiles, D. F. Stotz, and K. J. Zimmer. Version [Agosto 2014]. A classification of the bird species of South America. American Ornithologists' Union. http://www.museum.lsu.edu/~Remsen/SACCBaseline.html", "numDescendants": 0, "lastCrawled": "2021-12-01T00:38:01.205+00:00", "lastInterpreted": "2020-06-05T22:33:27.360+00:00", "issues": ["SCIENTIFIC_NAME_ASSEMBLED"], "synonym": false, "class": "Aves"}, {"key": 164480921, "nubKey": 2480328, "nameKey": 8949145, "taxonID": "urn:lsid:ubio.org:namebank:3851166", "kingdom": "Animalia", "phylum": "Chordata", "order": "Charadriiformes", "family": "Charadriidae", "genus": "Pluvialis", "species": "Pluvialis dominica", "kingdomKey": 164480645, "phylumKey": 164480647, "classKey": 164480649, "orderKey": 164480910, "familyKey": 164480914, "genusKey": 164480920, "speciesKey": 164480921, "datasetKey": "dc71df48-f5b0-4eb1-9be2-c632ebcb1bee", "parentKey": 164480920, "parent": "Pluvialis", "scientificName": "Pluvialis dominica (M\u00fcller, 1776)", "canonicalName": "Pluvialis dominica", "authorship": "(M\u00fcller, 1776) ", "nameType": "SCIENTIFIC", "rank": "SPECIES", "origin": "SOURCE", "taxonomicStatus": "ACCEPTED", "nomenclaturalStatus": [], "accordingTo": "Remsen, J. V., Jr., C. D. Cadena, A. Jaramillo, M. Nores, J. F. Pacheco, J. P\u00e9rez-Em\u00e1n, M. B. Robbins, F. G. Stiles, D. F. Stotz, and K. J. Zimmer. Version [Agosto 2014]. A classification of the bird species of South America. American Ornithologists' Union. http://www.museum.lsu.edu/~Remsen/SACCBaseline.html", "numDescendants": 0, "lastCrawled": "2021-12-01T00:38:02.911+00:00", "lastInterpreted": "2020-06-05T19:25:05.116+00:00", "issues": ["SCIENTIFIC_NAME_ASSEMBLED"], "synonym": false, "class": "Aves"}, {"key": 164571637, "nubKey": 2480328, "nameKey": 8949141, "taxonID": "https://www.gbif.org/species/2480328", "kingdom": "Animalia", "phylum": "Chordata", "order": "Charadriiforme", "family": "Charadriidae", "genus": "Pluvialis", "species": "Pluvialis dominica", "kingdomKey": 164571567, "phylumKey": 164571568, "classKey": 164571569, "orderKey": 164571634, "familyKey": 164571635, "genusKey": 164571636, "speciesKey": 164571637, "datasetKey": "72bb0c4b-2d8a-4d75-bcf4-b6693c3067b6", "parentKey": 164571636, "parent": "Pluvialis", "scientificName": "Pluvialis dominica", "canonicalName": "Pluvialis dominica", "authorship": "", "nameType": "SCIENTIFIC", "rank": "SPECIES", "origin": "SOURCE", "taxonomicStatus": "ACCEPTED", "nomenclaturalStatus": [], "numDescendants": 0, "lastCrawled": "2021-12-01T00:36:46.520+00:00", "lastInterpreted": "2020-06-13T04:16:52.984+00:00", "issues": [], "synonym": false, "class": "Aves"}, {"key": 165192901, "nubKey": 2480328, "nameKey": 8949159, "taxonID": "4169348", "order": "Charadriiformes", "family": "Charadriidae", "genus": "Pluvialis", "species": "Pluvialis dominica", "classKey": 100347857, "orderKey": 100508466, "familyKey": 195449929, "genusKey": 195449931, "speciesKey": 165192901, "datasetKey": "16c3f9cb-4b19-4553-ac8e-ebb90003aa02", "parentKey": 195449931, "parent": "Pluvialis", "scientificName": "Pluvialis dominica (Statius M\u00fcller, 1776)", "canonicalName": "Pluvialis dominica", "authorship": "(Statius M\u00fcller, 1776) ", "nameType": "SCIENTIFIC", "rank": "SPECIES", "origin": "SOURCE", "taxonomicStatus": "ACCEPTED", "nomenclaturalStatus": [], "numDescendants": 0, "references": "http://de.wikipedia.org/wiki/Wanderregenpfeifer", "lastCrawled": "2021-12-01T07:01:15.291+00:00", "lastInterpreted": "2022-05-18T20:13:12.047+00:00", "issues": ["SCIENTIFIC_NAME_ASSEMBLED"], "synonym": false, "class": "Aves"}, {"key": 165904899, "nubKey": 2480328, "nameKey": 33157240, "taxonID": "6640", "kingdom": "Animalia", "order": "Charadriiformes", "family": "Charadriidae", "genus": "Pluvialis", "species": "Pluvialis dominica", "kingdomKey": 100217010, "classKey": 100217014, "orderKey": 165905327, "familyKey": 165905017, "genusKey": 165904914, "speciesKey": 165904899, "datasetKey": "c696e5ee-9088-4d11-bdae-ab88daffab78", "parentKey": 165904914, "parent": "Pluvialis", "scientificName": "Pluvialis dominica (M\u00fcller & Pls, 1776)", "canonicalName": "Pluvialis dominica", "vernacularName": "American Golden Plover", "authorship": "(M\u00fcller & Pls, 1776) ", "nameType": "SCIENTIFIC", "rank": "SPECIES", "origin": "SOURCE", "taxonomicStatus": "ACCEPTED", "nomenclaturalStatus": [], "numDescendants": 0, "lastCrawled": "2022-05-25T20:46:03.736+00:00", "lastInterpreted": "2022-05-25T20:47:57.344+00:00", "issues": ["SCIENTIFIC_NAME_ASSEMBLED"], "synonym": false, "class": "Aves"}, {"key": 168017631, "nubKey": 2480328, "nameKey": 8949155, "taxonID": "3647", "kingdom": "Animalia", "phylum": "Chordata", "order": "Charadriiformes", "family": "Charadriidae", "genus": "Pluvialis", "species": "Pluvialis dominica", "kingdomKey": 167920784, "phylumKey": 168001715, "classKey": 168003099, "orderKey": 168016827, "familyKey": 168017574, "genusKey": 168017625, "speciesKey": 168017631, "datasetKey": "a6c6cead-b5ce-4a4e-8cf5-1542ba708dec", "parentKey": 168017625, "parent": "Pluvialis", "scientificName": "Pluvialis dominica (Statius Muller, 1776)", "canonicalName": "Pluvialis dominica", "authorship": "(Statius Muller, 1776) ", "nameType": "SCIENTIFIC", "rank": "SPECIES", "origin": "SOURCE", "taxonomicStatus": "ACCEPTED", "nomenclaturalStatus": [], "publishedIn": "Natursyst. Suppl. p. 116", "numDescendants": 0, "lastCrawled": "2022-05-17T14:19:28.487+00:00", "lastInterpreted": "2022-05-17T14:33:33.473+00:00", "issues": ["SCIENTIFIC_NAME_ASSEMBLED"], "synonym": false, "class": "Aves"}, {"key": 168513624, "nubKey": 2480328, "nameKey": 32273688, "taxonID": "MSTSNM:Arter:7ef9da42-0e0a-4626-b0ce-abc800da056f", "kingdom": "Animalia", "phylum": "Chordata", "order": "Charadriiformes", "family": "Charadriidae", "genus": "Pluvialis", "species": "Pluvialis dominica", "kingdomKey": 168508128, "phylumKey": 168511502, "classKey": 168513386, "orderKey": 168513562, "familyKey": 168513565, "genusKey": 168513615, "speciesKey": 168513624, "datasetKey": "4b3e4a71-704a-485c-917c-20a89944ea37", "parentKey": 168513615, "parent": "Pluvialis", "scientificName": "Pluvialis dominica (P.L. Statius M\u00fcller, 1776)", "canonicalName": "Pluvialis dominica", "authorship": "(P.L.Statius M\u00fcller, 1776) ", "nameType": "SCIENTIFIC", "rank": "SPECIES", "origin": "SOURCE", "taxonomicStatus": "ACCEPTED", "nomenclaturalStatus": [], "numDescendants": 0, "references": "https://arter.dk/taxa/taxon/details/b9fc2bf9-f785-ea11-aa77-501ac539d1ea", "lastCrawled": "2022-05-21T16:21:28.943+00:00", "lastInterpreted": "2022-05-21T16:25:15.748+00:00", "issues": [], "synonym": false, "class": "Aves"}, {"key": 170530145, "nubKey": 2480328, "nameKey": 8949141, "taxonID": "https://www.gbif.org/species/2480328", "kingdom": "Animalia", "phylum": "Chordata", "order": "Charadriiformes", "family": "Charadriidae", "genus": "Pluvialis", "species": "Pluvialis dominica", "kingdomKey": 170529822, "phylumKey": 170529823, "classKey": 170529824, "orderKey": 170530085, "familyKey": 170530143, "genusKey": 170530144, "speciesKey": 170530145, "datasetKey": "b73f8fb2-cb99-4dcf-b620-5a211ece20ec", "parentKey": 170530144, "parent": "Pluvialis", "scientificName": "Pluvialis dominica", "canonicalName": "Pluvialis dominica", "authorship": "", "nameType": "SCIENTIFIC", "rank": "SPECIES", "origin": "SOURCE", "taxonomicStatus": "ACCEPTED", "nomenclaturalStatus": [], "numDescendants": 0, "lastCrawled": "2021-12-01T00:16:55.583+00:00", "lastInterpreted": "2020-11-26T01:29:27.251+00:00", "issues": [], "synonym": false, "class": "Aves"}, {"key": 172732971, "nubKey": 2480328, "nameKey": 8949155, "taxonID": "4KKPW", "kingdom": "Animalia", "phylum": "Chordata", "order": "Charadriiformes", "family": "Charadriidae", "genus": "Pluvialis", "species": "Pluvialis dominica", "kingdomKey": 172331902, "phylumKey": 172636724, "classKey": 171152611, "orderKey": 172731069, "familyKey": 172732845, "genusKey": 172732957, "speciesKey": 172732971, "datasetKey": "7ddf754f-d193-4cc9-b351-99906754a03b", "constituentKey": "c2508dd9-c6dc-4312-879b-2b80d23dc6c1", "parentKey": 172732957, "parent": "Pluvialis", "scientificName": "Pluvialis dominica (Statius Muller, 1776)", "canonicalName": "Pluvialis dominica", "vernacularName": "American Golden Plover", "authorship": "(Statius Muller, 1776) ", "nameType": "SCIENTIFIC", "rank": "SPECIES", "origin": "SOURCE", "taxonomicStatus": "ACCEPTED", "nomenclaturalStatus": [], "numDescendants": 0, "references": "https://www.itis.gov/servlet/SingleRpt/SingleRpt?search_topic=TSN&search_value=176564", "lastCrawled": "2022-05-02T22:30:50.429+00:00", "lastInterpreted": "2022-05-03T04:03:14.943+00:00", "issues": ["NOMENCLATURAL_STATUS_INVALID"], "synonym": false, "class": "Aves"}, {"key": 176607792, "nubKey": 2480328, "nameKey": 8949145, "taxonID": "22693740", "kingdom": "Animalia", "phylum": "Chordata", "order": "Aves", "family": "Charadriidae", "genus": "Pluvialis", "species": "Pluvialis dominica", "kingdomKey": 192001797, "phylumKey": 192001850, "classKey": 192002129, "orderKey": 192002131, "familyKey": 192002223, "genusKey": 192002266, "speciesKey": 176607792, "datasetKey": "19491596-35ae-4a91-9a98-85cf505f1bd3", "parentKey": 192002266, "parent": "Pluvialis", "scientificName": "Pluvialis dominica (M\u00fcller, 1776)", "canonicalName": "Pluvialis dominica", "vernacularName": "American Golden Plover", "authorship": "(M\u00fcller, 1776) ", "nameType": "SCIENTIFIC", "rank": "SPECIES", "origin": "SOURCE", "taxonomicStatus": "ACCEPTED", "nomenclaturalStatus": [], "numDescendants": 0, "references": "https://apiv3.iucnredlist.org/api/v3/taxonredirect/22693740", "lastCrawled": "2022-01-12T12:18:42.444+00:00", "lastInterpreted": "2022-01-12T12:32:34.710+00:00", "issues": [], "synonym": false, "class": "Charadriiformes"}, {"key": 177704002, "nubKey": 2480328, "nameKey": 8949141, "taxonID": "240205", "kingdom": "Metazoa", "phylum": "Chordata", "order": "Charadriiformes", "family": "Charadriidae", "genus": "Pluvialis", "species": "Pluvialis dominica", "kingdomKey": 177651702, "phylumKey": 177654008, "classKey": 177656782, "orderKey": 177702994, "familyKey": 177703967, "genusKey": 177703996, "speciesKey": 177704002, "datasetKey": "6b6b2923-0a10-4708-b170-5b7c611aceef", "parentKey": 177703996, "parent": "Pluvialis", "scientificName": "Pluvialis dominica", "canonicalName": "Pluvialis dominica", "authorship": "", "nameType": "SCIENTIFIC", "rank": "SPECIES", "origin": "SOURCE", "taxonomicStatus": "ACCEPTED", "nomenclaturalStatus": [], "numDescendants": 0, "lastCrawled": "2022-05-21T06:57:42.944+00:00", "lastInterpreted": "2022-05-21T08:57:57.632+00:00", "issues": ["CLASSIFICATION_NOT_APPLIED"], "synonym": false, "class": "Aves"}, {"key": 180178626, "nubKey": 2480328, "nameKey": 33157240, "taxonID": "NHMSYS0000530777", "kingdom": "Animalia", "phylum": "Chordata", "order": "Charadriiformes", "family": "Charadriidae", "genus": "Pluvialis", "species": "Pluvialis dominica", "kingdomKey": 180120333, "phylumKey": 180172520, "classKey": 180172524, "orderKey": 180177530, "familyKey": 180178591, "genusKey": 180178625, "speciesKey": 180178626, "datasetKey": "dbaa27eb-29e7-4cbb-8eab-3f689cfce116", "parentKey": 180178625, "parent": "Pluvialis", "scientificName": "Pluvialis dominica (M\u00fcller & Pls, 1776)", "canonicalName": "Pluvialis dominica", "vernacularName": "American Golden Plover", "authorship": "(M\u00fcller & Pls, 1776) ", "nameType": "SCIENTIFIC", "rank": "SPECIES", "origin": "SOURCE", "taxonomicStatus": "ACCEPTED", "nomenclaturalStatus": [], "numDescendants": 0, "lastCrawled": "2021-12-21T13:29:00.608+00:00", "lastInterpreted": "2021-12-21T13:43:02.059+00:00", "issues": ["SCIENTIFIC_NAME_ASSEMBLED"], "synonym": false, "class": "Aves"}, {"key": 180178629, "nubKey": 2480328, "nameKey": 8949159, "taxonID": "NBNSYS0000000184", "kingdom": "Animalia", "phylum": "Chordata", "order": "Charadriiformes", "family": "Charadriidae", "genus": "Pluvialis", "species": "Pluvialis dominica", "kingdomKey": 180120333, "phylumKey": 180172520, "classKey": 180172524, "orderKey": 180177530, "familyKey": 180178591, "genusKey": 180178625, "speciesKey": 180178626, "datasetKey": "dbaa27eb-29e7-4cbb-8eab-3f689cfce116", "parentKey": 180178625, "parent": "Pluvialis", "acceptedKey": 180178626, "accepted": "Pluvialis dominica (M\u00fcller & Pls, 1776)", "scientificName": "Pluvialis dominica (Statius M\u00fcller, 1776)", "canonicalName": "Pluvialis dominica", "authorship": "(Statius M\u00fcller, 1776) ", "nameType": "SCIENTIFIC", "rank": "SPECIES", "origin": "SOURCE", "taxonomicStatus": "SYNONYM", "nomenclaturalStatus": [], "numDescendants": 0, "lastCrawled": "2021-12-21T13:29:00.608+00:00", "lastInterpreted": "2021-12-21T13:43:02.065+00:00", "issues": ["SCIENTIFIC_NAME_ASSEMBLED"], "synonym": true, "class": "Aves"}, {"key": 180178630, "nameKey": 41185053, "taxonID": "NBNSYS0100004777", "kingdom": "Animalia", "phylum": "Chordata", "order": "Charadriiformes", "family": "Charadriidae", "genus": "Pluvialis", "kingdomKey": 180120333, "phylumKey": 180172520, "classKey": 180172524, "orderKey": 180177530, "familyKey": 180178591, "genusKey": 180178625, "datasetKey": "dbaa27eb-29e7-4cbb-8eab-3f689cfce116", "parentKey": 180178625, "parent": "Pluvialis", "scientificName": "Pluvialis dominica/fulva agg.", "canonicalName": "Pluvialis dominica", "vernacularName": "Lesser Golden Plover", "authorship": "", "nameType": "SCIENTIFIC", "rank": "SPECIES_AGGREGATE", "origin": "SOURCE", "taxonomicStatus": "ACCEPTED", "nomenclaturalStatus": [], "numDescendants": 0, "lastCrawled": "2021-12-21T13:29:00.608+00:00", "lastInterpreted": "2021-12-21T13:43:02.067+00:00", "issues": ["BACKBONE_MATCH_NONE", "PARTIALLY_PARSABLE"], "synonym": false, "class": "Aves"}, {"key": 180457211, "nubKey": 2480328, "nameKey": 8949155, "taxonID": "404640", "kingdom": "Animalia", "phylum": "Chordata", "order": "Charadriiformes", "family": "Charadriidae", "genus": "Pluvialis", "kingdomKey": 187307327, "phylumKey": 187307375, "classKey": 187315681, "orderKey": 187315913, "familyKey": 187316097, "genusKey": 187316111, "datasetKey": "1ec61203-14fa-4fbd-8ee5-a4a80257b45a", "parentKey": 187316111, "parent": "Pluvialis", "acceptedKey": 131909992, "accepted": "Pluvialis fulva (J.F.Gmelin, 1789)", "scientificName": "Pluvialis dominica (Statius Muller, 1776)", "canonicalName": "Pluvialis dominica", "authorship": "(Statius Muller, 1776) ", "nameType": "SCIENTIFIC", "origin": "SOURCE", "taxonomicStatus": "SYNONYM", "nomenclaturalStatus": [], "numDescendants": 0, "lastCrawled": "2021-12-01T07:03:49.022+00:00", "lastInterpreted": "2021-09-07T07:07:36.538+00:00", "issues": ["SCIENTIFIC_NAME_ASSEMBLED"], "synonym": true, "class": "Aves"}, {"key": 181869705, "nubKey": 2480328, "nameKey": 8949145, "taxonID": "3DJYIOK389B", "kingdom": "Animalia", "phylum": "Chordata", "order": "Charadriiformes", "family": "Charadriidae", "genus": "Pluvialis", "species": "Pluvialis dominica", "kingdomKey": 195544768, "phylumKey": 195548896, "classKey": 195549714, "orderKey": 195549795, "familyKey": 195549816, "genusKey": 195549819, "speciesKey": 181869705, "datasetKey": "99dbc9e9-7b66-468c-92a6-897a5560ca26", "parentKey": 195549819, "parent": "Pluvialis", "scientificName": "Pluvialis dominica (M\u00fcller, 1776)", "canonicalName": "Pluvialis dominica", "vernacularName": "American Golden Plover", "authorship": "(M\u00fcller, 1776) ", "nameType": "SCIENTIFIC", "rank": "SPECIES", "origin": "SOURCE", "taxonomicStatus": "ACCEPTED", "nomenclaturalStatus": [], "numDescendants": 0, "references": "https://nederlandsesoorten.nl/nsr/concept/03DJYIOK389B", "lastCrawled": "2022-05-21T03:07:29.946+00:00", "lastInterpreted": "2022-05-21T03:08:38.039+00:00", "issues": ["VERNACULAR_NAME_INVALID"], "synonym": false, "class": "Aves"}, {"key": 182406822, "nubKey": 2480328, "nameKey": 8949145, "taxonID": "urn:lsid:catalogueoflife.org:taxon:d1d15b37-2dc5-11e0-98c6-2ce70255a436:col20120124", "kingdom": "Animalia", "phylum": "Chordata", "order": "Ciconiiformes", "family": "Charadriidae", "genus": "Pluvialis", "species": "Pluvialis dominica", "kingdomKey": 182406287, "phylumKey": 182406288, "classKey": 182406289, "orderKey": 182406586, "familyKey": 182406814, "genusKey": 182406820, "speciesKey": 182406822, "datasetKey": "592a1039-e00a-493d-abbd-b5f6051c14c6", "parentKey": 182406820, "parent": "Pluvialis", "scientificName": "Pluvialis dominica (M\u00fcller, 1776)", "canonicalName": "Pluvialis dominica", "authorship": "(M\u00fcller, 1776) ", "nameType": "SCIENTIFIC", "rank": "SPECIES", "origin": "SOURCE", "taxonomicStatus": "ACCEPTED", "nomenclaturalStatus": [], "numDescendants": 0, "lastCrawled": "2021-11-30T23:16:04.248+00:00", "lastInterpreted": "2021-05-28T17:52:27.007+00:00", "issues": ["SCIENTIFIC_NAME_ASSEMBLED", "DESCRIPTION_INVALID"], "synonym": false, "class": "Aves"}, {"key": 183835882, "nubKey": 2480328, "nameKey": 54603927, "taxonID": "TSN:176564", "kingdom": "Animalia", "phylum": "Chordata", "order": "Charadriiformes", "family": "Charadriidae", "genus": "Pluvialis", "species": "Pluvialis dominica", "kingdomKey": 183906462, "phylumKey": 183906463, "classKey": 183906464, "orderKey": 183906920, "familyKey": 183906943, "genusKey": 183906946, "speciesKey": 183835882, "datasetKey": "d79d388c-1f0e-49cb-80d7-93a47d7b5fd3", "parentKey": 183906946, "parent": "Pluvialis", "scientificName": "\"Pluvialis dominica (Statius Muller, 1776)\"", "canonicalName": "Pluvialis dominica", "authorship": "(Statius Muller, 1776) ", "nameType": "SCIENTIFIC", "rank": "SPECIES", "origin": "SOURCE", "taxonomicStatus": "ACCEPTED", "nomenclaturalStatus": [], "remarks": "Estatus AICA: CO4", "numDescendants": 0, "lastCrawled": "2021-12-01T06:56:42.421+00:00", "lastInterpreted": "2021-08-02T15:47:07.355+00:00", "issues": [], "synonym": false, "class": "Aves"}, {"key": 184626449, "nameKey": 55810813, "taxonID": "MSTSNM:Arter:505f64cb-2593-4c64-9052-ad8900f7d501", "kingdom": "Animalia", "phylum": "Chordata", "order": "Charadriiformes", "family": "Charadriidae", "genus": "Pluvialis", "kingdomKey": 168508128, "phylumKey": 168511502, "classKey": 168513386, "orderKey": 168513562, "familyKey": 168513565, "genusKey": 168513615, "datasetKey": "4b3e4a71-704a-485c-917c-20a89944ea37", "parentKey": 168513615, "parent": "Pluvialis", "scientificName": "Pluvialis dominica/fulva", "canonicalName": "Pluvialis dominica", "authorship": "", "nameType": "SCIENTIFIC", "rank": "SPECIES_AGGREGATE", "origin": "SOURCE", "taxonomicStatus": "ACCEPTED", "nomenclaturalStatus": [], "numDescendants": 0, "references": "https://arter.dk/taxa/taxon/details/8094de85-2b12-4f03-930c-ad8900f7d4e9", "lastCrawled": "2022-05-21T16:21:28.943+00:00", "lastInterpreted": "2022-05-21T16:25:15.751+00:00", "issues": ["BACKBONE_MATCH_NONE", "PARTIALLY_PARSABLE"], "synonym": false, "class": "Aves"}, {"key": 195584108, "nubKey": 2480328, "nameKey": 24683033, "taxonID": "https://www.gbif.org/species/2480328", "kingdom": "Animalia", "phylum": "Chordata", "order": "Charadriiformes", "family": "Charadriidae", "genus": "Pluvialis", "species": "Pluvialis dominica", "kingdomKey": 195584119, "phylumKey": 195584120, "classKey": 195584121, "orderKey": 195584136, "familyKey": 195584142, "genusKey": 195584143, "speciesKey": 195584108, "datasetKey": "3bbb9bf0-e68c-4a5c-a051-7e347585dba6", "parentKey": 195584143, "parent": "Pluvialis", "scientificName": "Pluvialis dominica Statius Muller, 1776", "canonicalName": "Pluvialis dominica", "authorship": "Statius Muller, 1776", "nameType": "SCIENTIFIC", "rank": "SPECIES", "origin": "SOURCE", "taxonomicStatus": "ACCEPTED", "nomenclaturalStatus": [], "numDescendants": 0, "lastCrawled": "2022-05-24T18:36:08.188+00:00", "lastInterpreted": "2022-05-24T18:36:10.053+00:00", "issues": ["SCIENTIFIC_NAME_ASSEMBLED"], "synonym": false, "class": "Aves"}]}